orcomics/ORC.py
orcomics/__init__.py
orcomics/graph_attributes.py
orcomics/util.py
orcomics-0.1.2.dist-info/LICENSE
orcomics-0.1.2.dist-info/METADATA
orcomics-0.1.2.dist-info/WHEEL
orcomics-0.1.2.dist-info/top_level.txt
orcomics-0.1.2.dist-info/RECORD
