Metadata-Version: 2.1
Name: orcomics
Version: 0.1.2
Summary: Ollivier-Ricci curvature for -omic network analysis
Author-email: Anish Simhal <aksimhal@gmail.com>
Project-URL: Homepage, https://github.com/aksimhal/ORC-Omics
Classifier: Programming Language :: Python :: 3
Classifier: License :: OSI Approved :: GNU General Public License v3 or later (GPLv3+)
Classifier: Operating System :: OS Independent
Requires-Python: >=3.8
License-File: LICENSE
Requires-Dist: scipy
Requires-Dist: numpy
Requires-Dist: networkx
Requires-Dist: pot
Requires-Dist: pandas
Requires-Dist: cmake
Requires-Dist: cvxpy
Requires-Dist: ecos
